[
    {
        "accuracy": 0.9903,
        "batch": 8,
        "best_accuracy": 0.9903,
        "best_epoch": 5,
        "dropout": 0.4742538147631196,
        "duration": 413235100822,
        "epoch_max": 5,
        "gpu_memory_kb": 3269962.0,
        "gradient_norm": 0.016396221864984444,
        "lr": 0.003333129435479131,
        "lr_now": 0.003333129435479131,
        "momentum": 0.7936904206103542,
        "samples_per_second": 702.7169105991204,
        "test_loss": 0.04291784247253455,
        "train_accuracy": 0.9947833333333334,
        "train_loss": 0.02275446572926098,
        "transform": "bf-v1-RandomAdjustSharpnes_RandomAutocontrast",
        "uid": "1176300b1d773de6ac23d47bcb8107f8"
    },
    {
        "accuracy": 0.9881,
        "batch": 128,
        "best_accuracy": 0.9881,
        "best_epoch": 5,
        "dropout": 0.11191479748874894,
        "duration": 85321687852,
        "epoch_max": 5,
        "gpu_memory_kb": 292226.5,
        "gradient_norm": 1.0138361693397622,
        "lr": 0.11153005082878574,
        "lr_now": 0.11153005082878574,
        "momentum": 0.7795486294823512,
        "samples_per_second": 3581.928897488514,
        "test_loss": 0.042756321106774325,
        "train_accuracy": 0.9916,
        "train_loss": 0.026224709185175915,
        "transform": "complex_32_flip",
        "uid": "8a8e2820cbdc90b4471baa526134b544"
    },
    {
        "accuracy": 0.9857,
        "batch": 512,
        "best_accuracy": 0.9863,
        "best_epoch": 4,
        "dropout": 0.23342880588309134,
        "duration": 193484795689,
        "epoch_max": 5,
        "gpu_memory_kb": 3269962.0,
        "gradient_norm": 2.999999023518377,
        "lr": 0.0324323782565525,
        "lr_now": 0.0324323782565525,
        "momentum": 0.628515457572514,
        "samples_per_second": 1553.6265800900067,
        "test_loss": 0.045556997507810594,
        "train_accuracy": 0.9873833333333333,
        "train_loss": 0.03937643577770914,
        "transform": "bf-v1-CenterCrop_RandomAdjustSharpnes_RandomGrayscale",
        "uid": "bdb08a5a6c05d8b369420f1382534d42"
    },
    {
        "accuracy": 0.2603,
        "batch": 32,
        "best_accuracy": 0.2603,
        "best_epoch": 5,
        "dropout": 0.019551864098259764,
        "duration": 122078805141,
        "epoch_max": 5,
        "gpu_memory_kb": 21078389.5,
        "gradient_norm": 0.208739045574701,
        "lr": 1.8485444487234362e-05,
        "lr_now": 1.8485444487234362e-05,
        "momentum": 0.8889981283114018,
        "samples_per_second": 2398.3449116739,
        "test_loss": 2.2946233147630295,
        "train_accuracy": 0.2590166666666667,
        "train_loss": 2.294789256922404,
        "transform": "norm",
        "uid": "a4238a2f7d0320125ff4fd3efc36a799"
    },
    {
        "accuracy": 0.1256,
        "batch": 2048,
        "best_accuracy": 0.1256,
        "best_epoch": 3,
        "dropout": 0.4695912915956162,
        "duration": 298448513936,
        "epoch_max": 5,
        "gpu_memory_kb": 21078389.5,
        "gradient_norm": 0.12910554478363573,
        "lr": 2.7931899389003306e-05,
        "lr_now": 2.7931899389003306e-05,
        "momentum": 0.5559961032800512,
        "samples_per_second": 1038.822941832549,
        "test_loss": 2.3022393703460695,
        "train_accuracy": 0.12448333333333333,
        "train_loss": 2.302275204658508,
        "transform": "bf-v1-RandomAdjustSharpnes_GaussianBlur_5",
        "uid": "a3784a41da6e7f83f496519f123914a4"
    }
]