[
    {
        "accuracy": 0.5424477566072526,
        "batch": 64,
        "best_accuracy": 0.5424477566072526,
        "best_epoch": 1,
        "dropout": 0.11176385506224262,
        "duration": 67419389337,
        "epoch_max": 5,
        "gpu_memory_kb": 772863.5,
        "gradient_norm": 2.321704299900608,
        "lr": 0.03748103346535546,
        "lr_now": 0.03748103346535546,
        "momentum": 0.789912790993705,
        "samples_per_second": 1086.5962927039923,
        "test_loss": 1.4358043115613501,
        "train_accuracy": 0.5973763599382994,
        "train_loss": 1.232856593954511,
        "transform": "norm_flip",
        "uid": "8e22d503d9e4a2dd9fdaac4bf47f3911"
    },
    {
        "accuracy": 0.2542255685310387,
        "batch": 64,
        "best_accuracy": 0.2542255685310387,
        "best_epoch": 1,
        "dropout": 0.2933527004023829,
        "duration": 277850890861,
        "epoch_max": 5,
        "gpu_memory_kb": 2934978.5,
        "gradient_norm": 2.82683966650357,
        "lr": 0.267603220855115,
        "lr_now": 0.267603220855115,
        "momentum": 0.17806743330161856,
        "samples_per_second": 263.656369453828,
        "test_loss": 2.68486779269188,
        "train_accuracy": 0.296108221739902,
        "train_loss": 2.3467617784525108,
        "transform": "bf-v1-RandomPosterize_RandomCrop_4",
        "uid": "f7f6ea557d30d6d5043475f4205b96bc"
    },
    {
        "accuracy": 0.21477412415488628,
        "batch": 64,
        "best_accuracy": 0.21477412415488628,
        "best_epoch": 1,
        "dropout": 0.01712987915327885,
        "duration": 124118042732,
        "epoch_max": 1,
        "gpu_memory_kb": 2979265.5,
        "gradient_norm": 1.9758939177333135,
        "lr": 0.011862996013843516,
        "lr_now": 0.011862996013843516,
        "momentum": 0.28191397076556135,
        "samples_per_second": 590.2236097471769,
        "test_loss": 2.234391162085006,
        "train_accuracy": 0.2264356989775721,
        "train_loss": 2.1872603748563075,
        "transform": "bf-v1-RandomCrop_RandomHorizontalFlip_5",
        "uid": "38acc7bd1d930ef56f96e55c227b3998"
    },
    {
        "accuracy": 0.2140058389674247,
        "batch": 16,
        "best_accuracy": 0.2140058389674247,
        "best_epoch": 1,
        "dropout": 0.4732666407424584,
        "duration": 250689417144,
        "epoch_max": 5,
        "gpu_memory_kb": 772863.5,
        "gradient_norm": 2.999999362583,
        "lr": 0.00032725408444329634,
        "lr_now": 0.00032725408444329634,
        "momentum": 0.5526428763916499,
        "samples_per_second": 292.2228227512501,
        "test_loss": 2.2137436652080957,
        "train_accuracy": 0.21917359433228223,
        "train_loss": 2.201817780479278,
        "transform": "bf-v1-Pad_38",
        "uid": "37681b357ae2e9369a89daed4a575132"
    },
    {
        "accuracy": 0.21077904118008606,
        "batch": 64,
        "best_accuracy": 0.21077904118008606,
        "best_epoch": 1,
        "dropout": 0.12334614861171744,
        "duration": 286322353660,
        "epoch_max": 5,
        "gpu_memory_kb": 20242411.5,
        "gradient_norm": 2.9999988755930405,
        "lr": 0.0005563682374779823,
        "lr_now": 0.0005563682374779823,
        "momentum": 0.6488069385364548,
        "samples_per_second": 255.85554271083046,
        "test_loss": 2.227579345867148,
        "train_accuracy": 0.209549940620009,
        "train_loss": 2.217751210016975,
        "transform": "bf-v1-RandomHorizontalFlip_RandomPosterize_4",
        "uid": "8735287b25956ea3fd8cf68c373f2bd3"
    },
    {
        "accuracy": 0.1958743085433313,
        "batch": 16,
        "best_accuracy": 0.1958743085433313,
        "best_epoch": 1,
        "dropout": 0.2767922614282244,
        "duration": 239954373699,
        "epoch_max": 5,
        "gpu_memory_kb": 772863.5,
        "gradient_norm": 2.999999418454295,
        "lr": 2.5912094001501487e-05,
        "lr_now": 2.5912094001501487e-05,
        "momentum": 0.6326908323445982,
        "samples_per_second": 305.2967914965219,
        "test_loss": 2.235542282489596,
        "train_accuracy": 0.18921058738414076,
        "train_loss": 2.2429904751862,
        "transform": "echo_64_flip",
        "uid": "b7ed74666a6c7bf79a5888eee1b30b03"
    },
    {
        "accuracy": 0.12161954517516903,
        "batch": 32,
        "best_accuracy": 0.12161954517516903,
        "best_epoch": 1,
        "dropout": 0.46408784753782495,
        "duration": 253091009654,
        "epoch_max": 5,
        "gpu_memory_kb": 20242411.5,
        "gradient_norm": 3.0000000629038506,
        "lr": 0.7791914512950643,
        "lr_now": 0.7791914512950643,
        "momentum": 0.5055382449794782,
        "samples_per_second": 289.4499567574294,
        "test_loss": 912533683740.9337,
        "train_accuracy": 0.11673969723029881,
        "train_loss": 773420267993.9912,
        "transform": "bf-v1-CenterCrop_RandomRotation_2",
        "uid": "710ea031e590847d596297287648a823"
    }
]