[
    {
        "accuracy": 0.2377,
        "batch": 256,
        "best_accuracy": 0.2377,
        "best_epoch": 3,
        "dropout": 0.00326985176163197,
        "duration": 82498962052,
        "epoch_max": 5,
        "gpu_memory_kb": 13903538.0,
        "gradient_norm": 2.9999996372133797,
        "lr": 0.015893431745879323,
        "lr_now": 0.015893431745879323,
        "momentum": 0.761802404164799,
        "samples_per_second": 1818.1482742056473,
        "test_loss": 3.3070392370224,
        "train_accuracy": 0.25058,
        "train_loss": 3.1893644381542594,
        "transform": "bf-v1-RandomHorizontalFlip_RandomCrop_4",
        "uid": "ad800d1ab81e324bfe09f63819b02a2d"
    },
    {
        "accuracy": 0.1813,
        "batch": 128,
        "best_accuracy": 0.1813,
        "best_epoch": 3,
        "dropout": 0.022911494802454357,
        "duration": 96250636920,
        "epoch_max": 5,
        "gpu_memory_kb": 13903538.0,
        "gradient_norm": 3.000000032746091,
        "lr": 0.0015165544817397779,
        "lr_now": 0.0015165544817397779,
        "momentum": 0.9161510370309988,
        "samples_per_second": 1562.9583856075499,
        "test_loss": 3.685149908065796,
        "train_accuracy": 0.22784,
        "train_loss": 3.3959961638731113,
        "transform": "bf-v1-Grayscale_RandomAdjustSharpnes_2",
        "uid": "3e779ed6d3234357f793cd7abc7ea694"
    },
    {
        "accuracy": 0.1084,
        "batch": 4096,
        "best_accuracy": 0.1084,
        "best_epoch": 3,
        "dropout": 0.04533549400803677,
        "duration": 95143812699,
        "epoch_max": 5,
        "gpu_memory_kb": 13903538.0,
        "gradient_norm": 2.9999995553448615,
        "lr": 0.008687330537645338,
        "lr_now": 0.008687330537645338,
        "momentum": 0.20109261696146197,
        "samples_per_second": 1579.2302100311585,
        "test_loss": 4.065488497416179,
        "train_accuracy": 0.11496,
        "train_loss": 4.0319941227252665,
        "transform": "bf-v1-RandomEqualize_RandomAutocontrast_2",
        "uid": "77296746e7937eea501f856a4377a3ed"
    },
    {
        "accuracy": 0.042,
        "batch": 16,
        "best_accuracy": 0.042,
        "best_epoch": 3,
        "dropout": 0.27671856214008156,
        "duration": 89193307797,
        "epoch_max": 5,
        "gpu_memory_kb": 13903538.0,
        "gradient_norm": 2.999999559819482,
        "lr": 1.517790472427049e-05,
        "lr_now": 1.517790472427049e-05,
        "momentum": 0.03256064046649154,
        "samples_per_second": 1673.0928463030837,
        "test_loss": 4.524703955078125,
        "train_accuracy": 0.0381,
        "train_loss": 4.519408411254883,
        "transform": "bf-v1-RandomEqualize_2",
        "uid": "e3519bee517ea3951e8e972a0c67c0c9"
    },
    {
        "accuracy": 0.0408,
        "batch": 64,
        "best_accuracy": 0.0408,
        "best_epoch": 3,
        "dropout": 0.474019173687059,
        "duration": 93296598663,
        "epoch_max": 5,
        "gpu_memory_kb": 276458.5,
        "gradient_norm": 2.9999997967933747,
        "lr": 2.7537230329761795e-05,
        "lr_now": 2.7537230329761795e-05,
        "momentum": 0.5373251322007309,
        "samples_per_second": 1627.4662911342275,
        "test_loss": 4.475449616741982,
        "train_accuracy": 0.04104,
        "train_loss": 4.46925630227989,
        "transform": "bf-v1-RandomGrayscale_Grayscale_2",
        "uid": "432547d05a204d7d821c7858102b962e"
    }
]