[
    {
        "accuracy": 0.9915,
        "batch": 64,
        "best_accuracy": 0.9915,
        "best_epoch": 5,
        "dropout": 0.2510625394476874,
        "duration": 674832584343,
        "epoch_max": 5,
        "gpu_memory_kb": 1590329.5,
        "gradient_norm": 1.1942518622050524,
        "lr": 0.057077245476574154,
        "lr_now": 0.057077245476574154,
        "momentum": 0.1846173203549204,
        "samples_per_second": 496.80713566584916,
        "test_loss": 0.027162525617904686,
        "train_accuracy": 0.9935666666666667,
        "train_loss": 0.019712344509131063,
        "transform": "echo_299",
        "uid": "fadf6c4610e68e936768d76f04723344"
    },
    {
        "accuracy": 0.9896,
        "batch": 128,
        "best_accuracy": 0.9896,
        "best_epoch": 5,
        "dropout": 0.24137332046544863,
        "duration": 127396954253,
        "epoch_max": 5,
        "gpu_memory_kb": 13814978.5,
        "gradient_norm": 1.4961276444234781,
        "lr": 0.037306875781477844,
        "lr_now": 0.037306875781477844,
        "momentum": 0.7751450620051381,
        "samples_per_second": 2358.115588767219,
        "test_loss": 0.03476346326941076,
        "train_accuracy": 0.9927833333333334,
        "train_loss": 0.021391555315443574,
        "transform": "bf-v1-RandomEqualize_RandomAutocontrast_2",
        "uid": "5f8b130fefb4f2a5eaae1c23ce367832"
    },
    {
        "accuracy": 0.9826,
        "batch": 64,
        "best_accuracy": 0.9826,
        "best_epoch": 5,
        "dropout": 0.2277555953455262,
        "duration": 160886864467,
        "epoch_max": 5,
        "gpu_memory_kb": 660173.5,
        "gradient_norm": 1.7193432843038083,
        "lr": 0.022596533516704754,
        "lr_now": 0.022596533516704754,
        "momentum": 0.5306997324832543,
        "samples_per_second": 1547.119571214565,
        "test_loss": 0.05570192399193202,
        "train_accuracy": 0.9851333333333333,
        "train_loss": 0.04680339502779318,
        "transform": "bf-v1-CenterCrop_RandomHorizontalFlip_2",
        "uid": "458429e97efbd04de7c4a42238314f9f"
    },
    {
        "accuracy": 0.9764,
        "batch": 128,
        "best_accuracy": 0.9764,
        "best_epoch": 5,
        "dropout": 0.16562212902901058,
        "duration": 234303649525,
        "epoch_max": 5,
        "gpu_memory_kb": 661648.5,
        "gradient_norm": 2.1604087241659578,
        "lr": 0.04642282746661673,
        "lr_now": 0.04642282746661673,
        "momentum": 0.11122692364275655,
        "samples_per_second": 1698.3041052278572,
        "test_loss": 0.06780610995697259,
        "train_accuracy": 0.9783666666666667,
        "train_loss": 0.06706459702713403,
        "transform": "bf-v1-RandomHorizontalFlip_RandomPosterize_RandomAdjustSharpnes",
        "uid": "c9defbbe9360c5d6aa74f8aa058e9668"
    },
    {
        "accuracy": 0.955,
        "batch": 512,
        "best_accuracy": 0.955,
        "best_epoch": 5,
        "dropout": 0.1466334693933934,
        "duration": 172968610465,
        "epoch_max": 5,
        "gpu_memory_kb": 1021038.5,
        "gradient_norm": 2.8537467556932627,
        "lr": 0.0381231533288717,
        "lr_now": 0.0381231533288717,
        "momentum": 0.44189013272800093,
        "samples_per_second": 1569.3070485674507,
        "test_loss": 0.14524032585322857,
        "train_accuracy": 0.95705,
        "train_loss": 0.1430631660051265,
        "transform": "bf-v1-CenterCrop_RandomSolarize_2",
        "uid": "86e0791f486501e30648370365206bcf"
    }
]