[
    {
        "accuracy": 0.8429,
        "batch": 32,
        "best_accuracy": 0.8476,
        "best_epoch": 21,
        "duration": 1102234312816,
        "epoch_max": 50,
        "gpu_memory_kb": 207629.5,
        "gradient_norm": 0.04180986563472909,
        "lr": 0.007134226199409181,
        "lr_now": 0.007134226199409181,
        "momentum": 0.9519550302563805,
        "samples_per_second": 1460.6900391563952,
        "test_loss": 0.7910628865083186,
        "train_accuracy": 0.99468,
        "train_loss": 0.016033624585293896,
        "transform": "bf-v1-RandomEqualize_RandomAdjustSharpnes_2",
        "uid": "49e77ae04435e1ce307ac34ceda257f2"
    },
    {
        "accuracy": 0.8261,
        "batch": 32,
        "best_accuracy": 0.8383,
        "best_epoch": 31,
        "duration": 1113545130956,
        "epoch_max": 50,
        "gpu_memory_kb": 207629.5,
        "gradient_norm": 2.9999996872322483,
        "lr": 0.007134226199409181,
        "lr_now": 0.007134226199409181,
        "momentum": 0.9519550302563805,
        "samples_per_second": 1435.736660704302,
        "test_loss": 0.9330167932727467,
        "train_accuracy": 0.99366,
        "train_loss": 0.019229212465632316,
        "transform": "bf-v1-RandomEqualize_RandomAdjustSharpnes_2",
        "uid": "bfd6f678f4b9877648f4154d904455c6"
    }
]