[
    {
        "accuracy": 0.8168,
        "batch": 8,
        "best_accuracy": 0.8266,
        "best_epoch": 9,
        "duration": 749480815599,
        "epoch_max": 50,
        "gpu_memory_kb": 588858.0,
        "gradient_norm": 1.2362876495669326,
        "lr": 0.03009259428123911,
        "lr_now": 0.03009259428123911,
        "momentum": 0.030813907544403163,
        "samples_per_second": 668.5636541798928,
        "test_loss": 0.7110175377994776,
        "train_accuracy": 0.98396,
        "train_loss": 0.04996904463599669,
        "transform": "bf-v1-RandomPosterize_CenterCrop_4",
        "uid": "1c86c3138ea5ca064a03b90d08f20331"
    }
]