[
    {
        "accuracy": 0.513375796178344,
        "batch": 128,
        "best_accuracy": 0.513375796178344,
        "best_epoch": 3,
        "duration": 479567556467,
        "epoch_max": 5,
        "gpu_memory_kb": 1518908.5,
        "gradient_norm": 3.6763177749675533,
        "lr": 0.0426459030843127,
        "lr_now": 0.0426459030843127,
        "momentum": 0.6088739244969191,
        "samples_per_second": 58.98487903744982,
        "test_loss": 1.608269339607608,
        "train_accuracy": 0.5477875171612631,
        "train_loss": 1.473964059675062,
        "transform": "bf-v1-Pad_RandomHorizontalFlip_RandomAdjustSharpnes",
        "uid": "24b615f43e0e8ea4f12d16c5666f64e6"
    },
    {
        "accuracy": 0.47286624203821653,
        "batch": 64,
        "best_accuracy": 0.47286624203821653,
        "best_epoch": 3,
        "duration": 694260446956,
        "epoch_max": 5,
        "gpu_memory_kb": 10783673.5,
        "gradient_norm": 7.936452022908183,
        "lr": 0.006519396535929559,
        "lr_now": 0.006519396535929559,
        "momentum": 0.4205332073592378,
        "samples_per_second": 40.624767541148614,
        "test_loss": 1.6226014043054273,
        "train_accuracy": 0.5008976660682226,
        "train_loss": 1.5261061425144609,
        "transform": "bf-v1-RandomHorizontalFlip_RandomAutocontrast_RandomPerspective_256",
        "uid": "d467fad4067e4497fe6ee510669b3ef2"
    },
    {
        "accuracy": 0.4354140127388535,
        "batch": 256,
        "best_accuracy": 0.4354140127388535,
        "best_epoch": 3,
        "duration": 588580952807,
        "epoch_max": 5,
        "gpu_memory_kb": 23366352.0,
        "gradient_norm": 5.501743016633747,
        "lr": 0.01416477584386191,
        "lr_now": 0.01416477584386191,
        "momentum": 0.4961861725157891,
        "samples_per_second": 48.653454014541154,
        "test_loss": 1.6530914530158043,
        "train_accuracy": 0.4608723202027669,
        "train_loss": 1.5716921026642259,
        "transform": "bf-v1-RandomAdjustSharpnes_RandomRotation_3",
        "uid": "92dd19e92efaddb0a3523a04800458c9"
    },
    {
        "accuracy": 0.2746496815286624,
        "batch": 16,
        "best_accuracy": 0.2746496815286624,
        "best_epoch": 3,
        "duration": 279640109777,
        "epoch_max": 5,
        "gpu_memory_kb": 1518908.5,
        "gradient_norm": 1.1458525306705432,
        "lr": 0.030996619714244708,
        "lr_now": 0.030996619714244708,
        "momentum": 0.8650102190645469,
        "samples_per_second": 101.78823094002544,
        "test_loss": 2.0737019985671936,
        "train_accuracy": 0.2840849086492766,
        "train_loss": 2.045919507943295,
        "transform": "bf-v1-CenterCrop_Pad_RandomHorizontalFlip",
        "uid": "21fb8e2fe2f4005291ea28954b7fd318"
    },
    {
        "accuracy": 0.21171974522292994,
        "batch": 1,
        "best_accuracy": 0.21171974522292994,
        "best_epoch": 3,
        "duration": 739917125409,
        "epoch_max": 5,
        "gpu_memory_kb": 23366352.0,
        "gradient_norm": 7.983786597629031,
        "lr": 0.010775678400937233,
        "lr_now": 0.010775678400937233,
        "momentum": 0.6296777746217571,
        "samples_per_second": 38.32126288585589,
        "test_loss": 2.338035471267927,
        "train_accuracy": 0.21776322737353468,
        "train_loss": 2.3142317881256553,
        "transform": "bf-v1-RandomGrayscale_Pad_5",
        "uid": "0271018eed862b27dc2feab166dab7ad"
    }
]