[
    {
        "accuracy": 0.7866472034419176,
        "batch": 4,
        "best_accuracy": 0.7866472034419176,
        "best_epoch": 4,
        "dropout": 0.12169289340129674,
        "duration": 719458889263,
        "epoch_max": 5,
        "gpu_memory_kb": 5321662.5,
        "gradient_norm": 1.291326499824119e-08,
        "lr": 0.0070844353368734675,
        "lr_now": 0.0070844353368734675,
        "momentum": 0.3220565736885006,
        "samples_per_second": 406.2290404827378,
        "test_loss": 1.1140790360515753,
        "train_accuracy": 0.845543770561175,
        "train_loss": 0.7756803968346712,
        "transform": "bf-v1-Pad_RandomEqualize_RandomAdjustSharpnes",
        "uid": "202cc57ee296810adb17083bd3823c13"
    },
    {
        "accuracy": 0.7021742470805162,
        "batch": 512,
        "best_accuracy": 0.7021742470805162,
        "best_epoch": 4,
        "dropout": 0.26478765441165203,
        "duration": 302661470200,
        "epoch_max": 5,
        "gpu_memory_kb": 5321662.5,
        "gradient_norm": 2.9999995884538198,
        "lr": 0.004383124190752481,
        "lr_now": 0.004383124190752481,
        "momentum": 0.8947373897958173,
        "samples_per_second": 969.6920960066478,
        "test_loss": 1.0072087096232993,
        "train_accuracy": 0.7398473865978678,
        "train_loss": 0.8687762067549758,
        "transform": "bf-v1-CenterCrop_RandomGrayscale_6",
        "uid": "db668bf7a8046d832a330157dc4277c7"
    },
    {
        "accuracy": 0.3368162261831592,
        "batch": 16,
        "best_accuracy": 0.3368162261831592,
        "best_epoch": 4,
        "dropout": 0.2111271978841423,
        "duration": 372746129411,
        "epoch_max": 5,
        "gpu_memory_kb": 21124102.5,
        "gradient_norm": 2.999999386871537,
        "lr": 0.00021173540707931446,
        "lr_now": 0.00021173540707931446,
        "momentum": 0.7689300041037501,
        "samples_per_second": 785.8873329965808,
        "test_loss": 2.0292498050618186,
        "train_accuracy": 0.35561106788429775,
        "train_loss": 1.9646017102857791,
        "transform": "bf-v1-RandomRotation_CenterCrop_6",
        "uid": "76fb1e5432a7718a0eb24e2ceb3906c1"
    },
    {
        "accuracy": 0.22768131530424093,
        "batch": 2048,
        "best_accuracy": 0.22768131530424093,
        "best_epoch": 4,
        "dropout": 0.4583242120725429,
        "duration": 350679742028,
        "epoch_max": 5,
        "gpu_memory_kb": 21124102.5,
        "gradient_norm": 0.32494129447937253,
        "lr": 0.00028982451641571384,
        "lr_now": 0.00028982451641571384,
        "momentum": 0.9781688994223482,
        "samples_per_second": 837.6173171371386,
        "test_loss": 2.225929315273578,
        "train_accuracy": 0.2160749143426567,
        "train_loss": 2.224727153778076,
        "transform": "bf-v1-RandomAutocontrast_CenterCrop",
        "uid": "cdad3ca08d86a8603d54ec7cf3405ec8"
    }
]