[
    {
        "accuracy": 0.9831,
        "batch": 64,
        "best_accuracy": 0.9831,
        "best_epoch": 1,
        "duration": 34273212657,
        "epoch_max": 5,
        "gpu_memory_kb": 23386768.0,
        "gradient_norm": 0.5279817744097882,
        "lr": 0.29944574697538257,
        "lr_now": 0.29944574697538257,
        "momentum": 0.6863748671498473,
        "samples_per_second": 1750.696816212911,
        "test_loss": 0.04845083884136295,
        "train_accuracy": 0.9828833333333333,
        "train_loss": 0.0568784648288927,
        "transform": "bf-v1-CenterCrop_RandomSolarize_2",
        "uid": "6cf77b90ed734d3879e0e9c5b3d4b051"
    },
    {
        "accuracy": 0.9713,
        "batch": 256,
        "best_accuracy": 0.9713,
        "best_epoch": 1,
        "duration": 48690508691,
        "epoch_max": 5,
        "gpu_memory_kb": 3742354.0,
        "gradient_norm": 0.5280649794576315,
        "lr": 0.8316662032993545,
        "lr_now": 0.8316662032993545,
        "momentum": 0.03051518041636858,
        "samples_per_second": 1232.2875205703092,
        "test_loss": 0.08480772485490888,
        "train_accuracy": 0.9703833333333334,
        "train_loss": 0.0913008819076609,
        "transform": "bf-v1-RandomRotation_RandomPosterize_5",
        "uid": "45075fe3bf95f8b0e46aba0142402f57"
    },
    {
        "accuracy": 0.9671,
        "batch": 128,
        "best_accuracy": 0.9671,
        "best_epoch": 1,
        "duration": 46115543900,
        "epoch_max": 5,
        "gpu_memory_kb": 1888652.0,
        "gradient_norm": 2.6727288246821783,
        "lr": 0.006134147352568751,
        "lr_now": 0.006134147352568751,
        "momentum": 0.8173099857249737,
        "samples_per_second": 1301.096356987891,
        "test_loss": 0.11185110661000768,
        "train_accuracy": 0.9634166666666667,
        "train_loss": 0.11612870463176068,
        "transform": "bf-v1-RandomHorizontalFlip_CenterCrop_Pad",
        "uid": "290c6361db5939987588cb745c812e9a"
    },
    {
        "accuracy": 0.933,
        "batch": 16,
        "best_accuracy": 0.933,
        "best_epoch": 1,
        "duration": 58232493066,
        "epoch_max": 5,
        "gpu_memory_kb": 23386768.0,
        "gradient_norm": 2.9999998518759585,
        "lr": 0.00015592294713831785,
        "lr_now": 0.00015592294713831785,
        "momentum": 0.9182045233095825,
        "samples_per_second": 1030.3665865644277,
        "test_loss": 0.20320420176275075,
        "train_accuracy": 0.9309833333333334,
        "train_loss": 0.21632136744360128,
        "transform": "bf-v1-RandomHorizontalFlip_RandomPosterize_4",
        "uid": "0553cb3f0799468e145031322b7af891"
    },
    {
        "accuracy": 0.7499,
        "batch": 64,
        "best_accuracy": 0.7499,
        "best_epoch": 1,
        "duration": 35889761996,
        "epoch_max": 5,
        "gpu_memory_kb": 1888652.0,
        "gradient_norm": 2.999999930945201,
        "lr": 4.36144521558549e-05,
        "lr_now": 4.36144521558549e-05,
        "momentum": 0.6839754787237526,
        "samples_per_second": 1671.813702173913,
        "test_loss": 1.536863215410026,
        "train_accuracy": 0.7402166666666666,
        "train_loss": 1.5464551042137877,
        "transform": "bf-v1-CenterCrop_RandomGrayscale_6",
        "uid": "4d6398903d5aea4cb60dde940b6bb704"
    },
    {
        "accuracy": 0.7283,
        "batch": 8,
        "duration": 43648233097,
        "epoch_max": 1,
        "lr": 1.4926813268430817e-05,
        "momentum": 0.6688621031076895,
        "transform": "bf-v1-Pad_RandomAdjustSharpnes_RandomAutocontrast",
        "uid": "ed5dfd221a4966ecaeac7887ddab45eb"
    }
]