[
    {
        "accuracy": 0.9907,
        "batch": 64,
        "best_accuracy": 0.9907,
        "best_epoch": 3,
        "duration": 103025284086,
        "epoch_max": 5,
        "gpu_memory_kb": 23386768.0,
        "gradient_norm": 0.5122554137652989,
        "lr": 0.29944574697538257,
        "lr_now": 0.29944574697538257,
        "momentum": 0.6863748671498473,
        "samples_per_second": 1750.4984796930332,
        "test_loss": 0.029229021441450218,
        "train_accuracy": 0.9916,
        "train_loss": 0.025850423141912587,
        "transform": "bf-v1-CenterCrop_RandomSolarize_2",
        "uid": "397794ec205cc9f9f25d3b919ee59b1b"
    },
    {
        "accuracy": 0.9784,
        "batch": 256,
        "best_accuracy": 0.9822,
        "best_epoch": 2,
        "duration": 145699909107,
        "epoch_max": 5,
        "gpu_memory_kb": 3742354.0,
        "gradient_norm": 0.8255777350990944,
        "lr": 0.8316662032993545,
        "lr_now": 0.8316662032993545,
        "momentum": 0.03051518041636858,
        "samples_per_second": 1237.9287309451895,
        "test_loss": 0.06761539739381987,
        "train_accuracy": 0.9791166666666666,
        "train_loss": 0.06780307597302376,
        "transform": "bf-v1-RandomRotation_RandomPosterize_5",
        "uid": "eba8bea06eb4fc64893cc0307ba1e585"
    },
    {
        "accuracy": 0.977,
        "batch": 128,
        "best_accuracy": 0.977,
        "best_epoch": 3,
        "duration": 138009609319,
        "epoch_max": 5,
        "gpu_memory_kb": 1888652.0,
        "gradient_norm": 2.52397971351321,
        "lr": 0.006134147352568751,
        "lr_now": 0.006134147352568751,
        "momentum": 0.8173099857249737,
        "samples_per_second": 1309.1993483685949,
        "test_loss": 0.0652048229976687,
        "train_accuracy": 0.9790333333333333,
        "train_loss": 0.065306084599894,
        "transform": "bf-v1-RandomHorizontalFlip_CenterCrop_Pad",
        "uid": "52f41b3e508fa64edd4d19731fa01080"
    },
    {
        "accuracy": 0.9641,
        "batch": 16,
        "best_accuracy": 0.9641,
        "best_epoch": 3,
        "duration": 173317287595,
        "epoch_max": 5,
        "gpu_memory_kb": 23386768.0,
        "gradient_norm": 2.999999866028951,
        "lr": 0.00015592294713831785,
        "lr_now": 0.00015592294713831785,
        "momentum": 0.9182045233095825,
        "samples_per_second": 1023.5259929657241,
        "test_loss": 0.11013948716190644,
        "train_accuracy": 0.962,
        "train_loss": 0.12014311286841209,
        "transform": "bf-v1-RandomHorizontalFlip_RandomPosterize_4",
        "uid": "b2c2eb5feaf60179d37dd4796d31973f"
    },
    {
        "accuracy": 0.8817,
        "batch": 64,
        "best_accuracy": 0.8817,
        "best_epoch": 3,
        "duration": 107785076519,
        "epoch_max": 5,
        "gpu_memory_kb": 1888652.0,
        "gradient_norm": 2.9999996136860507,
        "lr": 4.36144521558549e-05,
        "lr_now": 4.36144521558549e-05,
        "momentum": 0.6839754787237526,
        "samples_per_second": 1669.6180377643743,
        "test_loss": 0.7173168744630875,
        "train_accuracy": 0.8715666666666667,
        "train_loss": 0.7387793622672685,
        "transform": "bf-v1-CenterCrop_RandomGrayscale_6",
        "uid": "9da3e44c0d52fb8093d2ffe159b6d646"
    }
]