[
    {
        "accuracy": 0.8188,
        "batch": 4,
        "best_accuracy": 0.8194,
        "best_epoch": 28,
        "duration": 1575577208684,
        "epoch_max": 50,
        "gpu_memory_kb": 2561641.0,
        "gradient_norm": 2.9999998228668687,
        "lr": 0.013301078716177599,
        "lr_now": 0.013301078716177599,
        "momentum": 0.3794143566253907,
        "samples_per_second": 990.0576366078726,
        "test_loss": 0.9603927785710861,
        "train_accuracy": 0.99814,
        "train_loss": 0.008678933228273837,
        "transform": "bf-v1-RandomCrop_CenterCrop_RandomAutocontrast",
        "uid": "bdd4468115061c1ed09ae6dd1f4508a6"
    }
]