[
    {
        "accuracy": 0.3311,
        "batch": 64,
        "duration": 19116203447,
        "epoch_max": 50,
        "lr": 0.005490980410148027,
        "momentum": 0.44840230862003094,
        "transform": "bf-v1-CenterCrop_RandomAdjustSharpnes_RandomGrayscale",
        "uid": "b9926314b279e33bc39931d6a429e812"
    },
    {
        "accuracy": 0.3278,
        "batch": 64,
        "duration": 27363756705,
        "lr": 0.005490980410148027,
        "momentum": 0.44840230862003094,
        "transform": "bf-v1-CenterCrop_RandomAdjustSharpnes_RandomGrayscale",
        "uid": "0289b329566956b917dda1d49ad1b0ba"
    },
    {
        "accuracy": 0.3168,
        "batch": 64,
        "duration": 26626870751,
        "lr": 0.007068524779215446,
        "momentum": 0.2809769701949192,
        "transform": "bf-v1-RandomHorizontalFlip_RandomPosterize_4",
        "uid": "d78a4df2d048cc66a2a32291a801ac42"
    },
    {
        "accuracy": 0.2532,
        "batch": 1024,
        "duration": 24396428180,
        "lr": 0.01200951034510711,
        "momentum": 0.506507181804819,
        "transform": "bf-v1-CenterCrop_RandomAdjustSharpnes_4",
        "uid": "1d676bc413d6ae0eb62ba5d007ff0aed"
    },
    {
        "accuracy": 0.1926,
        "batch": 2,
        "best_accuracy": 0.1926,
        "best_epoch": 2,
        "duration": 319323011497,
        "epoch_max": 5,
        "gpu_memory_kb": 19898.0,
        "gradient_norm": 0.9999998505923634,
        "lr": 0.0001358505036304714,
        "lr_now": 0.0001358505036304714,
        "momentum": 0.28462761210108634,
        "samples_per_second": 314.04109353247424,
        "test_loss": 2.1971904924392702,
        "train_accuracy": 0.19334,
        "train_loss": 2.2010062062740325,
        "transform": "bf-v1-RandomEqualize_RandomAutocontrast_2",
        "uid": "0dae7789e590f695d84ce68734a40d59"
    }
]