[
    {
        "accuracy": 0.8252,
        "batch": 8,
        "best_accuracy": 0.8293,
        "best_epoch": 11,
        "duration": 1244405954327,
        "epoch_max": 50,
        "gpu_memory_kb": 423929.0,
        "gradient_norm": 0.07616285374346853,
        "lr": 0.03454692943963246,
        "lr_now": 0.03454692943963246,
        "momentum": 0.4994996772760806,
        "samples_per_second": 684.1029135285801,
        "test_loss": 0.8589831648032703,
        "train_accuracy": 0.9982,
        "train_loss": 0.006865363778731785,
        "transform": "bf-v1-RandomGrayscale_80",
        "uid": "ecdb6962c2739ed6c8995ed46899d125"
    }
]