[
    {
        "accuracy": 0.6661,
        "batch": 128,
        "best_accuracy": 0.6661,
        "best_epoch": 2,
        "duration": 64931034865,
        "epoch_max": 50,
        "gpu_memory_kb": 1338920.0,
        "gradient_norm": 2.999999435051889,
        "lr": 0.06472968264945922,
        "lr_now": 0.06472968264945922,
        "momentum": 0.7638540417531691,
        "samples_per_second": 1541.8889855066234,
        "test_loss": 0.9606685676152193,
        "train_accuracy": 0.679,
        "train_loss": 0.9292912832306474,
        "transform": "bf-v1-RandomCrop_RandomAdjustSharpnes_RandomAutocontrast",
        "uid": "4508fc69243597ee109b2c7be0ebc3ce"
    },
    {
        "accuracy": 0.6372,
        "batch": 128,
        "duration": 27553988719,
        "epoch_max": 5,
        "lr": 0.06472968264945922,
        "momentum": 0.7638540417531691,
        "transform": "bf-v1-RandomCrop_RandomAdjustSharpnes_RandomAutocontrast",
        "uid": "f5bb2bdffdceb8f03bcc1047797c39ee"
    },
    {
        "accuracy": 0.6258,
        "batch": 4,
        "duration": 120990825146,
        "epoch_max": 5,
        "lr": 0.02407421853417919,
        "momentum": 0.0573042549963203,
        "transform": "bf-v1-RandomEqualize_CenterCrop_4",
        "uid": "1ef1171a14b164a3870d6b62ec395595"
    },
    {
        "accuracy": 0.5126,
        "batch": 128,
        "duration": 24002965667,
        "epoch_max": 5,
        "lr": 0.007106383003009941,
        "momentum": 0.43036517336277813,
        "transform": "bf-v1-CenterCrop_RandomPosterize_5",
        "uid": "c6cec92423a009af543a9cd6436f0ca3"
    },
    {
        "accuracy": 0.4244,
        "batch": 1024,
        "best_accuracy": 0.4244,
        "best_epoch": 2,
        "duration": 142111633243,
        "epoch_max": 5,
        "gpu_memory_kb": 6082258.0,
        "gradient_norm": 0.7415803808399668,
        "lr": 0.669806733272719,
        "lr_now": 0.669806733272719,
        "momentum": 0.8749272137811697,
        "samples_per_second": 691.961217054415,
        "test_loss": 1.5499268531799317,
        "train_accuracy": 0.42278,
        "train_loss": 1.5513849672006101,
        "transform": "bf-v1-RandomAutocontrast_CenterCrop",
        "uid": "ddfd869b3b210452f8fa0c0b27c558f6"
    },
    {
        "accuracy": 0.3839,
        "batch": 2048,
        "best_accuracy": 0.3839,
        "best_epoch": 2,
        "duration": 59779631983,
        "epoch_max": 5,
        "gpu_memory_kb": 3469954.5,
        "gradient_norm": 1.81134351907299,
        "lr": 0.015889830584902027,
        "lr_now": 0.015889830584902027,
        "momentum": 0.14260323651249418,
        "samples_per_second": 1740.6034934732215,
        "test_loss": 1.75511691570282,
        "train_accuracy": 0.37682,
        "train_loss": 1.7652155590057372,
        "transform": "norm",
        "uid": "9b7e0956142ecb72fbd6c98ef94af3c5"
    }
]