[
    {
        "accuracy": 0.9792,
        "batch": 4,
        "best_accuracy": 0.9792,
        "best_epoch": 4,
        "dropout": 0.061605044841822165,
        "duration": 688340693241,
        "epoch_max": 5,
        "gpu_memory_kb": 739306.5,
        "gradient_norm": 2.3627587941706065e-05,
        "lr": 0.004669737326962182,
        "lr_now": 0.004669737326962182,
        "momentum": 0.4549103406680526,
        "samples_per_second": 335.75651393459367,
        "test_loss": 0.07808106790146094,
        "train_accuracy": 0.98225,
        "train_loss": 0.07834138530832754,
        "transform": "norm_299_flip",
        "uid": "d190c869f65af46244ef300b013788de"
    },
    {
        "accuracy": 0.9622,
        "batch": 512,
        "best_accuracy": 0.9622,
        "best_epoch": 4,
        "dropout": 0.3223149643239543,
        "duration": 104986811849,
        "epoch_max": 5,
        "gpu_memory_kb": 20442716.0,
        "gradient_norm": 2.600679083033795,
        "lr": 0.03990140669884319,
        "lr_now": 0.03990140669884319,
        "momentum": 0.6688333213647764,
        "samples_per_second": 2286.139293727372,
        "test_loss": 0.11968461703509092,
        "train_accuracy": 0.9571166666666666,
        "train_loss": 0.13914884235394204,
        "transform": "bf-v1-RandomPerspective_103",
        "uid": "745fe20cc2f0ed3941f542758ced2245"
    },
    {
        "accuracy": 0.9463,
        "batch": 1024,
        "best_accuracy": 0.9463,
        "best_epoch": 4,
        "dropout": 0.2591176542922258,
        "duration": 165919277632,
        "epoch_max": 5,
        "gpu_memory_kb": 992798.0,
        "gradient_norm": 1.033450988788715,
        "lr": 0.15044351663729957,
        "lr_now": 0.15044351663729957,
        "momentum": 0.40365064356997526,
        "samples_per_second": 1449.0768605251014,
        "test_loss": 0.17871676981449128,
        "train_accuracy": 0.9459166666666666,
        "train_loss": 0.18581491481449644,
        "transform": "bf-v1-Pad_RandomAdjustSharpnes_RandomPosterize",
        "uid": "b3c652f816ca9207312857fd7f902282"
    },
    {
        "accuracy": 0.9178,
        "batch": 512,
        "best_accuracy": 0.9527,
        "best_epoch": 3,
        "dropout": 0.2525951518123143,
        "duration": 151347323793,
        "epoch_max": 5,
        "gpu_memory_kb": 992798.0,
        "gradient_norm": 2.5768802182556296,
        "lr": 0.08498656878074227,
        "lr_now": 0.08498656878074227,
        "momentum": 0.46201181214181375,
        "samples_per_second": 1587.5677218625879,
        "test_loss": 0.2875800088047981,
        "train_accuracy": 0.9204833333333333,
        "train_loss": 0.26653955523240364,
        "transform": "bf-v1-Pad_CenterCrop",
        "uid": "93131a7776daf98582f36edff1d2fea6"
    },
    {
        "accuracy": 0.8514,
        "batch": 16,
        "best_accuracy": 0.9698,
        "best_epoch": 2,
        "dropout": 0.2776245132012117,
        "duration": 188722661110,
        "epoch_max": 5,
        "gpu_memory_kb": 677587.5,
        "gradient_norm": 0.022748174708935164,
        "lr": 0.07553448476506543,
        "lr_now": 0.07553448476506543,
        "momentum": 0.7399122758209113,
        "samples_per_second": 1290.8769682466416,
        "test_loss": 1.2419055809486572,
        "train_accuracy": 0.854,
        "train_loss": 1.1431747836362018,
        "transform": "bf-v1-RandomEqualize_CenterCrop_4",
        "uid": "4d55539feeb017775f4b9a8595fdb761"
    }
]