[
    {
        "accuracy": 0.8973048792706142,
        "batch": 16,
        "best_accuracy": 0.8973048792706142,
        "best_epoch": 3,
        "duration": 1127361294313,
        "epoch_max": 5,
        "gpu_memory_kb": 63410.0,
        "gradient_norm": 0.9999998103153623,
        "lr": 0.015870050645011437,
        "lr_now": 0.015870050645011437,
        "momentum": 0.014777755950168947,
        "samples_per_second": 433.9242236644656,
        "test_loss": 0.24410101841800871,
        "train_accuracy": 0.9051422252257787,
        "train_loss": 0.2285357399583478,
        "transform": "bf-v1-Pad_RandomHorizontalFlip_5",
        "uid": "c6f1485b828949826a03bbc9cec3b259"
    },
    {
        "accuracy": 0.756938182546839,
        "batch": 32,
        "best_accuracy": 0.756938182546839,
        "best_epoch": 3,
        "duration": 1177483627595,
        "epoch_max": 5,
        "gpu_memory_kb": 108466.0,
        "gradient_norm": 0.9999999057131109,
        "lr": 0.00027500976280148316,
        "lr_now": 0.00027500976280148316,
        "momentum": 0.8512333084718465,
        "samples_per_second": 414.94163345762314,
        "test_loss": 0.5084825095553429,
        "train_accuracy": 0.7559316827425201,
        "train_loss": 0.5076048009951456,
        "transform": "bf-v1-RandomPerspective_CenterCrop",
        "uid": "d00efc66ed5490c6871d0785f6195667"
    },
    {
        "accuracy": 0.6591022943592827,
        "batch": 8,
        "best_accuracy": 0.6591022943592827,
        "best_epoch": 3,
        "duration": 972535878660,
        "epoch_max": 5,
        "gpu_memory_kb": 108466.0,
        "gradient_norm": 0.9999999588378082,
        "lr": 3.653330594122978e-05,
        "lr_now": 3.653330594122978e-05,
        "momentum": 0.06634440743612258,
        "samples_per_second": 501.96423246492316,
        "test_loss": 0.6240971877048604,
        "train_accuracy": 0.6590342200651226,
        "train_loss": 0.6233580723905081,
        "transform": "bf-v1-CenterCrop_Pad_RandomCrop",
        "uid": "2e3739cdca251b7578f4bb1119e23b90"
    }
]